LICENSE
MANIFEST.in
README.md
setup.cfg
setup.py
arjunarth/__init__.py
arjunarth/config.py
arjunarth.egg-info/PKG-INFO
arjunarth.egg-info/SOURCES.txt
arjunarth.egg-info/dependency_links.txt
arjunarth.egg-info/top_level.txt
arjunarth/Clients/__init__.py
arjunarth/Clients/client.py
arjunarth/Clients/pytgcalls.py
arjunarth/blacklist/__init__.py
arjunarth/blacklist/support.py
arjunarth/button/__init__.py
arjunarth/button/button.py
arjunarth/extra/__init__.py
arjunarth/extra/hosted.py
arjunarth/help/__init__.py
arjunarth/help/help.py
arjunarth/helper/__init__.py
arjunarth/helper/basic.py
arjunarth/helper/call.py
arjunarth/helper/data.py
arjunarth/helper/ekankth.py
arjunarth/helper/goblok.py
arjunarth/helper/hacking.py
arjunarth/helper/inline.py
arjunarth/helper/interval.py
arjunarth/helper/parser.py
arjunarth/helper/repo.py
arjunarth/helper/sticker.py
arjunarth/helper/tools.py
arjunarth/helper/utility.py
arjunarth/helper/what.py
arjunarth/methods/__init__.py
arjunarth/methods/queue.py
arjunarth/py_trans/__init__.py
arjunarth/py_trans/async_translator.py
arjunarth/py_trans/errors.py
arjunarth/py_trans/language_codes.py
arjunarth/py_trans/translator.py
arjunarth/pyrogram/__init__.py
arjunarth/pyrogram/_wrappers.py
arjunarth/pyrogram/func.py
arjunarth/pyrogram/misc.py
arjunarth/pyrogram/sections.py
arjunarth/pyrogram/toolbot.py
arjunarth/pyrogram/tools.py